visu_pandas/__init__.py
visu_pandas/visu_pandas.py
info_pandas_wbb-1.0.2.dist-info/METADATA
info_pandas_wbb-1.0.2.dist-info/WHEEL
info_pandas_wbb-1.0.2.dist-info/top_level.txt
info_pandas_wbb-1.0.2.dist-info/RECORD
