Metadata-Version: 2.1
Name: info-pandas-wbb
Version: 1.0.2
Summary: Teste lib para informações de tabela pandas
Home-page: 
Author: William Brandão Bilatto
Author-email: williambilatto@gmail.com
License: MIT
